climl/__init__.py
climl/main.py
climl-0.1.7.dist-info/METADATA
climl-0.1.7.dist-info/WHEEL
climl-0.1.7.dist-info/entry_points.txt
climl-0.1.7.dist-info/RECORD
