Metadata-Version: 2.1
Name: climl
Version: 0.1.7
Summary: 
Author: CLIML
Author-email: hello@climl.com
Requires-Python: >=3.11,<4.0
Classifier: Programming Language :: Python :: 3
Classifier: Programming Language :: Python :: 3.11
Classifier: Programming Language :: Python :: 3.12
Requires-Dist: catboost (>=1.2.2,<2.0.0)
Requires-Dist: flaml[automl] (>=2.1.1,<3.0.0)
Requires-Dist: lightgbm (>=4.1.0,<5.0.0)
Requires-Dist: packaging (>=23.2,<24.0)
Requires-Dist: py-autoclean (>=1.1.3,<2.0.0)
Requires-Dist: requests (>=2.31.0,<3.0.0)
Requires-Dist: typer[all] (>=0.9.0,<0.10.0)
